LICENSE.txt
evo_bridge_fastapi/__init__.py
evo_bridge_fastapi/assets/favicon.ico
evo_bridge_fastapi/assets/logo.png
evo_bridge_fastapi/assets/logo.txt
evo_bridge_fastapi/assets/logo1.png
evo_bridge_fastapi/assets/logo_80.txt
evo_bridge_fastapi/assets/logo_hd.txt
evo_bridge_fastapi/assets/qrcode.png
evo_bridge_fastapi/assets/style.css
evo_bridge_fastapi/assets/styles.css
evo_bridge_fastapi/assets_template/index.html
evo_bridge_fastapi/control/CFastApiServer.py
evo_bridge_fastapi/entity/__init__.py
evo_bridge_fastapi/tests/assets/logo.png
evo_bridge_fastapi/tests/test_evo_package_bridge_fastapi.py
evo_bridge_fastapi-2024.10.30202.dist-info/LICENSE.txt
evo_bridge_fastapi-2024.10.30202.dist-info/METADATA
evo_bridge_fastapi-2024.10.30202.dist-info/WHEEL
evo_bridge_fastapi-2024.10.30202.dist-info/RECORD
