Metadata-Version: 2.1
Name: evo-bridge-fastapi
Version: 2024.10.30202
Summary: evo-bridge-fastapi python
License: CC BY-NC-ND 4.0
Author: cyborg-ai-git
Author-email: 129898917+cyborg-ai-git@users.noreply.github.com
Requires-Python: >=3.10,<4.0
Classifier: License :: Other/Proprietary License
Classifier: Programming Language :: Python :: 3
Classifier: Programming Language :: Python :: 3.10
Classifier: Programming Language :: Python :: 3.11
Classifier: Programming Language :: Python :: 3.12
Requires-Dist: Jinja2 (>=3.1.4,<4.0.0)
Requires-Dist: evo-framework
Requires-Dist: evo-package-tunnel
Requires-Dist: fastapi (>=0.103.2,<0.104.0)
Requires-Dist: uvicorn (>=0.25.0,<0.26.0)
